acme_splunk_handler_zuul-1.0.0.dist-info/licenses/LICENSE
splunk_handler_zuul/__init__.py
acme_splunk_handler_zuul-1.0.0.dist-info/METADATA
acme_splunk_handler_zuul-1.0.0.dist-info/WHEEL
acme_splunk_handler_zuul-1.0.0.dist-info/top_level.txt
acme_splunk_handler_zuul-1.0.0.dist-info/RECORD
